{
  "$schema": "https://raw.githubusercontent.com/jetify-com/devbox/0.13.7/.schema/devbox.schema.json",
  "packages": [
    "bat@latest",
    "neovim@latest",
    "mise@latest",
    "aichat@latest",
    "awscli2@latest",
    "bun@latest",
    "curl@latest",
    "delta@latest",
    "deno@latest",
    "dust@latest",
    "fd@latest",
    "fre@latest",
    "gh@latest",
    "git@latest",
    "gitui@latest",
    "graphviz@latest",
    "gron@latest",
    "hyperfine@latest",
    "jq@latest",
    "jujutsu@latest",
    "just@latest",
    "nodejs_22@latest",
    "python313@latest",
    "ripgrep@latest",
    "terraform@latest",
    "tmux@latest",
    "typos@latest",
    "unison@latest",
    "universal-ctags@latest",
    "vim@latest",
    "vscode-langservers-extracted@latest",
    "watchexec@latest",
    "zoxide@latest"
  ],
  "shell": {
    "init_hook": [],
    "scripts":   {}
  }
}
